Workbook

Sheet Radio
A1: Fecha | B1: Día | C1: Radiodifusora | D1: Programa | E1: Titular | F1: Dependencia | G1: Tema | H1: Canal | I1: Estatus | J1: Clasificación | K1: Autor | L1: Género | M1: Recuento
A2: 46323 | B2: =IF(Información1[[#This Row],[Fecha]]='Ajuste de fechas'!$A$2,"Día actual","Día anterior") -> Día anterior | C2: Acir 92.5 FM | D2: Panorama Informativo | E2: Radioescucha Karen Zepeda. «Muy buenos días, licenciado Larrieta, para comentarte que en la colonia Juan C. Doria llevamos una semana sin agua...» | F2: Sipdus | G2: Abasto De Agua | H2: RADIO LOCAL | I2: Negativa | J2: Gobierno del estado | K2: Radioescucha | L2: Opinión | M2: 1
A3: 46323 | B3: =IF(Información1[[#This Row],[Fecha]]='Ajuste de fechas'!$A$2,"Día actual","Día anterior") -> Día anterior | C3: Acir 92.5 FM | D3: Panorama Informativo | E3: Radioescucha dice: “Hola, muy buenos días, Lalo Larrieta. Disculpe la molestia, pero en Rinconadas de San Francisco, Mineral de la Reforma, tenemos tres días sin agua “ | F3: Sipdus | G3: Abasto De Agua | H3: RADIO LOCAL | I3: Negativa | J3: Gobierno del estado | K3: Radioescucha | L3: Opinión | M3: 1
A4: 46323 | B4: =IF(Información1[[#This Row],[Fecha]]='Ajuste de fechas'!$A$2,"Día actual","Día anterior") -> Día anterior | C4: NQ 90.1 FM | D4: Enlace Hidalgo1 | E4: Locutor Jesús Riveros da lectura a comentario de radioescucha que reporta, la falta de suministro de agua potable en el fraccionamiento El Palmar, en la capital del estado de Hidalgo. Ante esta situación, se realizó un llamado de atención a la CAASIM para conocer las causas y la posible solución a esta problemática que afecta a los habitantes de la zona. | F4: Sipdus | G4: Abasto De Agua | H4: RADIO LOCAL | I4: Negativa | J4: Gobierno del estado | K4: Radioescucha | L4: Opinión | M4: 1
A5: 46323 | B5: =IF(Información1[[#This Row],[Fecha]]='Ajuste de fechas'!$A$2,"Día actual","Día anterior") -> Día anterior | C5: Ke Buena 106.7 FM | D5: Noticias 106.7 | E5: Locutor David Cárdenas destacó la labor de la Secretaría de Agricultura y Desarrollo Rural (Saderh) encabezada por Napoleón González Pérez, enfocada en dotar de herramientas e insumos a los productores del campo de Nopala para hacer más rentable y eficiente su labor. Asimismo, se enfatizó la necesidad de impulsar programas exclusivos para las nuevas generaciones de hijos de campesinos, buscando motivar el relevo generacional ante el abandono que el campo ha sufrido por parte de administraciones anteriores y brindarles mayores oportunidades de desarrollo productivo. | F5: Saderh | G5: Apoyo Al Agro | H5: RADIO LOCAL | I5: Positiva | J5: Gobierno del estado | K5: David Cárdenas | L5: Opinión | M5: 1
A6: 46323 | B6: =IF(Información1[[#This Row],[Fecha]]='Ajuste de fechas'!$A$2,"Día actual","Día anterior") -> Día anterior | C6: Ke Buena 106.7 FM | D6: Noticias 106.7 | E6: La Secretaría de Agricultura y Desarrollo Rural de Hidalgo (Saderh) anunció un programa enfocado en apoyar a las nuevas generaciones de hijos de campesinos dedicados al sector agropecuario, con el fin de facilitar herramientas que hagan más rentable y eficiente el trabajo de la tierra. Este anuncio se dio durante una reunión en Nopala, donde se entregaron 2,918,088 pesos en insumos agrícolas y pecuarios —como semillas, aves, ganado porcino, herramientas y árboles frutales— a 481 productores de la región. En el evento estuvieron presentes alcaldes de Nopala de Villagrán, Huichapan, Tecozautla y Chapantongo para coordinar acciones en favor del desarrollo rural | F6: Saderh | G6: Apoyo Al Agro | H6: RADIO LOCAL | I6: Positiva | J6: Gobierno del estado | K6: David Cárdenas | L6: Noticia | M6: 1
A7: 46323 | B7: =IF(Información1[[#This Row],[Fecha]]='Ajuste de fechas'!$A$2,"Día actual","Día anterior") -> Día anterior | C7: NQ 90.1 FM | D7: Enlace Hidalgo1 | E7: La ventanilla recibe solicitudes para análisis de suelos, instalación de invernaderos para mujeres y subsidios por afectaciones agrícolas y pecuarias. Productores agrícolas y pecuarios de Tulancingo podrán solicitar apoyos estatales hasta este miércoles 28 de octubre, a través de una ventanilla habilitada por la Secretaría del Campo municipal para gestionar programas de análisis de suelos, instalación de invernaderos y atención a catástrofes en el sector rural. La recepción de documentos se realiza de 8:30 a 16:00 horas en la Dirección de Gestión y Fomento. Los requisitos varían según el programa y, para resolver dudas, la dependencia puso a disposición el teléfono 775 755 8450, extensión 1239. Entre los apoyos disponibles se encuentra Análisis de Suelos, que contempla la toma de muestras. Las personas interesadas deben presentar identificación oficial vigente, CURP actualizado y comprobante de domicilio. El componente Mujeres que Transforman el Campo, destinado al establecimiento de módulos de invernadero, requiere además acreditar la propiedad o posesión legal del terreno, entregar un croquis para ubicarlo y presentar una carta bajo protesta de decir verdad que confirme que el predio cuenta con tierra apta para cultivo y agua suficiente para el riego. Para acceder a los subsidios por catástrofes agrícolas y pecuarias, los solicitantes deberán entregar fotografías impresas que permitan identificar las afectaciones parciales o totales en sus cultivos o unidades productivas. La Secretaría del Campo municipal informó que estas gestiones buscan acercar a los productores los programas impulsados por el Gobierno de Hidalgo y fortalecer las actividades agrícolas y pecuarias, de las que dependen numerosas familias. La coordinación con los gobiernos estatal y federal busca ampliar el acceso a recursos y herramientas para atender las necesidades del sector rural y mejorar las condiciones de quienes trabajan la tierra. | F7: Ayuntamiento | G7: Apoyo Al Agro | H7: RADIO LOCAL | I7: Informativa | J7: Alcaldías | K7: Jesús Riveros | L7: Noticia | M7: 1
A8: 46323 | B8: =IF(Información1[[#This Row],[Fecha]]='Ajuste de fechas'!$A$2,"Día actual","Día anterior") -> Día anterior | C8: NQ 90.1 FM | D8: Enlace Hidalgo1 | E8: Hidalgo apuesta por el futuro del campo con oportunidades para jóvenes | F8: Saderh | G8: Apoyo Al Agro | H8: RADIO LOCAL | I8: Positiva | J8: Gobierno del estado | K8: Juan Carlos Santamaría | L8: Boletín | M8: 1
A9: 46323 | B9: =IF(Información1[[#This Row],[Fecha]]='Ajuste de fechas'!$A$2,"Día actual","Día anterior") -> Día anterior | C9: Súper Stéreo 100.5 FM | D9: Enfoque Regional Matutino | E9: Entrevista con Miguel Saviñón sobre sus aspiraciones políticas y la estructura del PVEM en Tula. En la línea telefónica al delegado municipal del Partido Verde Ecologista de México (PVEM) aquí en Tula, el licenciado Miguel Saviñón, mi querido Saviñón, Savi como muchos también lo conocen, ¿cómo estás? Buenos días. "Muy bien, amigo Cristian, muchísimas gracias por la oportunidad, atesoro de sobremanera el espacio y un saludo muy cordial para toda la audiencia que sé que es muy vasta de este noticiero Retrovisor y de Super Estéreo. Muchas gracias, mi querido Miguel Saviñón, pues tenemos la oportunidad de poderte conocer y de verte a lo largo de los años también cómo te has desarrollado aquí en Tula ahora como delegado municipal del Partido Verde Ecologista de México y bueno pues se empiezan a correr también ya los procesos, procesos que serán para conocer quiénes irán dentro de ellos y quiénes participarán el siguiente año y saber y conocer de tu viva voz, mi querido Saviñón, si tú vas a participar, si tú quisieras estar dentro de esta contienda. Fíjate amigo que durante el transitar en la vida pública, en la política, pues siempre he tenido yo aspiraciones personales, sin embargo siempre he sido yo muy prudente y he seguido lo que ha indicado la dirigencia de cada uno de los institutos políticos donde he militado. Hoy en el Partido Verde Ecologista todavía no está nada definido, por supuesto que si en algún momento el partido dispone de mi perfil para estar dentro de la candidatura a la contienda para la presidencia municipal, pues lo haré yo con mucho entusiasmo y con mucho compromiso, sin embargo aún no se sabe, hoy estamos muy enfocados en seguir trabajando, en seguir aceitando la maquinaria de las estructuras del Partido Verde, estamos con el programa de la afiliación y seguir trabajando muy cercanos a la gente con propuestas muy sostenibles y sustentables en el tema ambiental, en el tema social y eso es lo que ahorita estamos muy enfocados en mi posición como delegado municipal del Partido Verde aquí en Tula y pues seguir invitando a la gente a que se sume a un proyecto donde tenemos muchas propuestas y muchas ideas innovadoras para Tula y por supuesto mucho compromiso y muchas muchas ganas de hacer las cosas bien." | F9: Congreso | G9: Aspirantes | H9: RADIO LOCAL | I9: Informativa | J9: Otros | K9: Christian García | L9: Entrevista | M9: 1
A10: 46323 | B10: =IF(Información1[[#This Row],[Fecha]]='Ajuste de fechas'!$A$2,"Día actual","Día anterior") -> Día anterior | C10: Acir 92.5 FM | D10: Panorama Informativo | E10: Eulalio Larrieta agradece Hans Islas del ayuntamiento de Mineral de la Reforma , por su apoyo en pasar los reportes. | F10: Ayuntamiento | G10: Atención a la ciudadanía | H10: RADIO LOCAL | I10: Positiva | J10: Alcaldías | K10: Eulalio Larrieta | L10: Opinión | M10: 1
A11: 46323 | B11: =IF(Información1[[#This Row],[Fecha]]='Ajuste de fechas'!$A$2,"Día actual","Día anterior") -> Día anterior | C11: Acir 92.5 FM | D11: Panorama Informativo | E11: Eulalio Larrieta informa que Jorge Hernández del ayuntamiento de Pachuca, esta al pendiente de todos los reportes de la ciudadania del Municipio de Pachuca | F11: Ayuntamiento | G11: Atención a la ciudadanía | H11: RADIO LOCAL | I11: Positiva | J11: Alcaldías | K11: Eulalio Larrieta | L11: Opinión | M11: 1
A12: 46323 | B12: =IF(Información1[[#This Row],[Fecha]]='Ajuste de fechas'!$A$2,"Día actual","Día anterior") -> Día anterior | C12: Acir 92.5 FM | D12: Panorama Informativo | E12: Eulalio Larrieta agradece a Carlos Gamiño por estar al pendiente de temas. | F12: Congreso | G12: Atención a la ciudadanía | H12: RADIO LOCAL | I12: Positiva | J12: Otros | K12: Eulalio Larrieta | L12: Opinión | M12: 1
A13: 46323 | B13: =IF(Información1[[#This Row],[Fecha]]='Ajuste de fechas'!$A$2,"Día actual","Día anterior") -> Día anterior | C13: Acir 92.5 FM | D13: Panorama Informativo | E13: Eulalio Larrieta agradece a Uriel Ramirez y Jair Martínez de la SEGOBH, porque esta al pendiente de lo que se necesite y los reportes. | F13: Segobh | G13: Atención a la ciudadanía | H13: RADIO LOCAL | I13: Positiva | J13: Gobierno del estado | K13: Eulalio Larrieta | L13: Opinión | M13: 1
... A83: 46324 | B83: =IF(Información1[[#This Row],[Fecha]]='Ajuste de fechas'!$A$2,"Día actual","Día anterior") -> Día actual | C83: Súper Stéreo 100.5 FM | D83: Enfoque Regional Matutino | E83: Fiesta de las Almas recorrerá Pachuca este viernes con 1,333 participantes, 42 contingentes y 25 carros alegóricos para celebrar el Día de Muertos. Los detalles con Joselyn Sánchez."Pachuca se prepara para recibir el desfile Fiesta de las Almas que se realizará este viernes 30 de octubre con la participación de 1,337 personas distribuidas en 42 contingentes provenientes de 20 municipios y sedes de Hidalgo, además de 25 carros alegóricos. El recorrido iniciará a las cinco de la tarde en el Centro Cultural del Ferrocarril y concluirá alrededor de las seis y media en el Reloj Monumental tras recorrer 3.4 kilómetros. Entre los participantes destacan comparsas de Xantolo de Yahualica, Huazalingo y Lolotla, así como agrupaciones de Pacula, Xochicoatlán y otros municipios que mostrarán las tradiciones del Día de Muertos. La secretaria de Cultura, Neida Naranjo Baltazar, destacó que esta celebración busca preservar la identidad y las costumbres de los pueblos hidalguenses. El desfile será gratuito, por lo que se espera la asistencia de familias y visitantes al centro de Pachuca. Para Enfoque Regional informó Joselyn Sánchez." | F83: Cultura | G83: Xantolo | H83: RADIO LOCAL | I83: Informativa | J83: Gobierno del estado | K83: Christian García | L83: Noticia | M83: 1

Sheet Ajuste de fechas
A1: Día actual | B1: Día anterior
A2: =TODAY() -> 46324 | B2: =A2-1 -> 46323
